ds_utils/__init__.py
ds_utils/math_utils.py
ds_utils/metrics.py
ds_utils/preprocess.py
ds_utils/strings.py
ds_utils/unsupervised.py
ds_utils/xai.py
data_science_utils-1.9.0.dist-info/METADATA
data_science_utils-1.9.0.dist-info/WHEEL
data_science_utils-1.9.0.dist-info/licenses/LICENSE
data_science_utils-1.9.0.dist-info/RECORD
