Metadata-Version: 2.4
Name: data_science_utils
Version: 1.9.0
Summary: Data Science Utils extends the Scikit-Learn API and Matplotlib API to provide simple methods that simplify tasks and visualizations for data science projects.
Project-URL: Homepage, https://github.com/idanmoradarthas/DataScienceUtils
Project-URL: Documentation, https://datascienceutils.readthedocs.io/en/latest/
Project-URL: Issues, https://github.com/idanmoradarthas/DataScienceUtils/issues
Project-URL: Repository, https://github.com/idanmoradarthas/DataScienceUtils.git
Project-URL: Changelog, https://github.com/idanmoradarthas/DataScienceUtils/blob/master/CHANGELOG.md
Author-email: Idan Morad <idanmorad.arthas@gmail.com>
License: MIT
License-File: LICENSE
Keywords: data-science,machine-learning,matplotlib,plotly,python,scikit-learn,utilities
Classifier: Development Status :: 5 - Production/Stable
Classifier: Framework :: Matplotlib
Classifier: Framework :: Pytest
Classifier: Framework :: tox
Classifier: Intended Audience :: Developers
Classifier: Intended Audience :: Education
Classifier: Intended Audience :: Science/Research
Classifier: License :: OSI Approved :: MIT License
Classifier: Programming Language :: Python :: 3.10
Classifier: Programming Language :: Python :: 3.11
Classifier: Programming Language :: Python :: 3.12
Classifier: Programming Language :: Python :: 3.13
Classifier: Topic :: Scientific/Engineering :: Artificial Intelligence
Classifier: Topic :: Utilities
Requires-Python: >=3.10
Requires-Dist: joblib>=1.2.0
Requires-Dist: matplotlib>=3.8.4
Requires-Dist: numpy>=1.26.3
Requires-Dist: pandas>=2.1.4
Requires-Dist: plotly>=6.1.1
Requires-Dist: pydotplus>=2.0.2
Requires-Dist: scikit-learn>=1.2.2
Requires-Dist: scipy>=1.11.4
Requires-Dist: seaborn>=0.12.2
